literature_search/__init__.py
literature_search/api_clients.py
literature_search/cli.py
literature_search/config_loader.py
literature_search/criteria_mapper.py
literature_search/keywords.py
literature_search/prisma_flow_diagram.drawio
literature_search/prisma_logs.py
literature_search/utils.py
literature_search-0.0.3.dist-info/METADATA
literature_search-0.0.3.dist-info/WHEEL
literature_search-0.0.3.dist-info/entry_points.txt
literature_search-0.0.3.dist-info/top_level.txt
literature_search-0.0.3.dist-info/RECORD
