Metadata-Version: 2.1
Name: literature-search
Version: 0.0.3
Summary: This package search for literature on multiple databases and allow uses to filter them using PRISMA method
Author-email: Shanaka Prageeth <wasp.bites.jp@gmail.com>
License: GPL-3.0-only
Project-URL: Homepage, https://github.com/shanakaprageeth/literature_search
Project-URL: Issues, https://github.com/shanakaprageeth/literature_search/issues
Classifier: Programming Language :: Python :: 3
Classifier: Operating System :: OS Independent
Classifier: License :: OSI Approved :: GNU General Public License v3 (GPLv3)
Requires-Python: >=3.9
Requires-Dist: matplotlib>=3.10.3
Requires-Dist: drawpyo>=0.2.2
Requires-Dist: requests
